Metadata-Version: 2.1
Name: odoo12-addon-l10n-it-vat-statement-split-payment
Version: 12.0.1.0.2
Summary: Migliora la liquidazione dell'IVA tenendo in considerazione la scissione dei pagamenti
Home-page: https://github.com/OCA/l10n-italy
Author: Openforce Srls Unipersonale, Odoo Community Association (OCA)
Author-email: support@odoo-community.org
License: AGPL-3
Platform: UNKNOWN
Classifier: Programming Language :: Python
Classifier: Framework :: Odoo
Classifier: License :: OSI Approved :: GNU Affero General Public License v3
Classifier: Development Status :: 4 - Beta
Requires-Python: >=3.5
Requires-Dist: odoo12-addon-account-vat-period-end-statement
Requires-Dist: odoo12-addon-l10n-it-split-payment
Requires-Dist: odoo (<12.1dev,>=12.0a)
